aitoolbox/__init__.py
aitoolbox/cloud/__init__.py
aitoolbox/cloud/AWS/__init__.py
aitoolbox/cloud/AWS/data_access.py
aitoolbox/cloud/AWS/model_load.py
aitoolbox/cloud/AWS/model_save.py
aitoolbox/cloud/AWS/results_save.py
aitoolbox/cloud/AWS/simple_email_service.py
aitoolbox/cloud/GoogleCloud/__init__.py
aitoolbox/cloud/GoogleCloud/data_access.py
aitoolbox/cloud/GoogleCloud/model_load.py
aitoolbox/cloud/GoogleCloud/model_save.py
aitoolbox/cloud/GoogleCloud/results_save.py
aitoolbox/experiment/__init__.py
aitoolbox/experiment/experiment_saver.py
aitoolbox/experiment/local_experiment_saver.py
aitoolbox/experiment/training_history.py
aitoolbox/experiment/core_metrics/__init__.py
aitoolbox/experiment/core_metrics/abstract_metric.py
aitoolbox/experiment/core_metrics/classification.py
aitoolbox/experiment/core_metrics/regression.py
aitoolbox/experiment/local_load/__init__.py
aitoolbox/experiment/local_load/local_model_load.py
aitoolbox/experiment/local_save/__init__.py
aitoolbox/experiment/local_save/folder_create.py
aitoolbox/experiment/local_save/local_model_save.py
aitoolbox/experiment/local_save/local_results_save.py
aitoolbox/experiment/result_package/__init__.py
aitoolbox/experiment/result_package/abstract_result_packages.py
aitoolbox/experiment/result_package/basic_packages.py
aitoolbox/experiment/result_package/hf_evaluate_packages.py
aitoolbox/experiment/result_package/torch_metrics_packages.py
aitoolbox/experiment/result_reporting/__init__.py
aitoolbox/experiment/result_reporting/hyperparam_reporter.py
aitoolbox/experiment/result_reporting/report_generator.py
aitoolbox/nlp/__init__.py
aitoolbox/nlp/torch_collate_fns.py
aitoolbox/nlp/core/__init__.py
aitoolbox/nlp/core/core.py
aitoolbox/nlp/core/vocabulary.py
aitoolbox/nlp/experiment_evaluation/NLP_metrics.py
aitoolbox/nlp/experiment_evaluation/NLP_result_package.py
aitoolbox/nlp/experiment_evaluation/__init__.py
aitoolbox/nlp/experiment_evaluation/attention_heatmap.py
aitoolbox/torchtrain/__init__.py
aitoolbox-1.8.0.dist-info/LICENSE
aitoolbox-1.8.0.dist-info/METADATA
aitoolbox-1.8.0.dist-info/WHEEL
aitoolbox-1.8.0.dist-info/top_level.txt
aitoolbox-1.8.0.dist-info/RECORD
