Metadata-Version: 2.1
Name: aitoolbox
Version: 1.8.0
Summary: PyTorch Model Training and Experiment Tracking Framework
Home-page: https://github.com/mv1388/AIToolbox
Author: Marko Vidoni
Author-email: 
License: MIT
Keywords: PyTorch,deep learning,research,train loop
Classifier: Development Status :: 4 - Beta
Classifier: Intended Audience :: Developers
Classifier: Topic :: Scientific/Engineering :: Artificial Intelligence
Classifier: License :: OSI Approved :: MIT License
Classifier: Programming Language :: Python :: 3
Classifier: Programming Language :: Python :: 3.9
Requires-Python: >=3.9.0
License-File: LICENSE
Requires-Dist: torch (>=1.12.0)
Requires-Dist: torchvision
Requires-Dist: torchtext
Requires-Dist: pytorch-nlp
Requires-Dist: transformers
Requires-Dist: numpy
Requires-Dist: pandas
Requires-Dist: scikit-learn
Requires-Dist: matplotlib
Requires-Dist: seaborn
Requires-Dist: tqdm
Requires-Dist: awscli
Requires-Dist: boto3
Requires-Dist: botocore
Requires-Dist: google-cloud-storage
Requires-Dist: nltk
Requires-Dist: pyrouge
Requires-Dist: rouge
Requires-Dist: tensorboard
Requires-Dist: wandb
